gmapi/__init__.py
gmapi/cli.py
gmapi/code.py
gmapi/constants.py
gmapi/gmapi.py
gmapi-1.17.30.dist-info/METADATA
gmapi-1.17.30.dist-info/RECORD
gmapi-1.17.30.dist-info/WHEEL
gmapi-1.17.30.dist-info/entry_points.txt
gmapi-1.17.30.dist-info/top_level.txt
